commonpower/__init__.py
commonpower/core.py
commonpower/control/__init__.py
commonpower/control/controllers.py
commonpower/control/environments.py
commonpower/control/observation_handling.py
commonpower/control/parsing.py
commonpower/control/pytupli_interface.py
commonpower/control/runners.py
commonpower/control/util.py
commonpower/control/wrappers.py
commonpower/control/configs/__init__.py
commonpower/control/configs/algorithms.py
commonpower/control/logging_utils/__init__.py
commonpower/control/logging_utils/callbacks.py
commonpower/control/logging_utils/loggers.py
commonpower/control/safety_layer/__init__.py
commonpower/control/safety_layer/penalties.py
commonpower/control/safety_layer/safety_layers.py
commonpower/data_forecasting/__init__.py
commonpower/data_forecasting/base.py
commonpower/data_forecasting/data_generators.py
commonpower/data_forecasting/data_sources.py
commonpower/data_forecasting/forecasters.py
commonpower/data_forecasting/nn_forecasting/__init__.py
commonpower/data_forecasting/nn_forecasting/config.py
commonpower/data_forecasting/nn_forecasting/data_splitting.py
commonpower/data_forecasting/nn_forecasting/dataset_wrappers.py
commonpower/data_forecasting/nn_forecasting/eval_metrics.py
commonpower/data_forecasting/nn_forecasting/models.py
commonpower/data_forecasting/nn_forecasting/nn_forecasting.py
commonpower/data_forecasting/nn_forecasting/nn_tuner.py
commonpower/data_forecasting/nn_forecasting/stopper.py
commonpower/data_forecasting/nn_forecasting/transform.py
commonpower/extensions/__init__.py
commonpower/extensions/cost_allocation.py
commonpower/extensions/factories.py
commonpower/extensions/network_import.py
commonpower/modeling/__init__.py
commonpower/modeling/base.py
commonpower/modeling/history.py
commonpower/modeling/mip_builder.py
commonpower/modeling/param_initialization.py
commonpower/modeling/robust_constraints.py
commonpower/modeling/robust_cost.py
commonpower/modeling/util.py
commonpower/models/__init__.py
commonpower-0.6.2.dist-info/METADATA
commonpower-0.6.2.dist-info/WHEEL
commonpower-0.6.2.dist-info/licenses/LICENSE
commonpower-0.6.2.dist-info/RECORD
