Metadata-Version: 2.4
Name: commonpower
Version: 0.6.2
Summary: A package for the exploration of safe single/multi-agent reinforcement learning in smart grids.
Project-URL: Homepage, https://github.com/TUMcps/commonpower
Project-URL: Documentation, https://commonpower.readthedocs.io
Author-email: Michael Eichelbeck <michael.eichelbeck@tum.de>, Hannah Markgraf <hannah.markgraf@tum.de>
License: MIT
License-File: LICENSE
Keywords: Control,Multi-Agent Systems,Power System,Reinforcement learning,Safety,Simulation,Smart Grid
Classifier: License :: OSI Approved :: MIT License
Classifier: Operating System :: OS Independent
Classifier: Programming Language :: Python :: 3
Requires-Python: <3.13,>=3.11
Requires-Dist: d3rlpy<3.0,>=2.8.1
Requires-Dist: gurobipy<13.0,>=12.0.3
Requires-Dist: jsonpickle<5.0,>=4.1.1
Requires-Dist: matplotlib<4.0,>=3.10.6
Requires-Dist: numpy<3.0,>=2.3.2
Requires-Dist: pandapower<4.0,>=3.1.2
Requires-Dist: prettytable<4.0,>=3.16.0
Requires-Dist: pydantic<3.0,>=2.11.7
Requires-Dist: pymongo<5.0,>=4.14.1
Requires-Dist: pyomo<7.0,>=6.9.4
Requires-Dist: stable-baselines3<3.0,>=2.7.0
Requires-Dist: tensorboard<3.0,>=2.20.0
Requires-Dist: tqdm<5.0,>=4.67.1
Requires-Dist: wandb<1.0,>=0.21.3
Provides-Extra: ci
Requires-Dist: pytest<9.0,>=8.4.1; extra == 'ci'
Provides-Extra: docs
Requires-Dist: myst-parser<5.0,>=4.0.1; extra == 'docs'
Requires-Dist: nbsphinx<1.0,>=0.9.7; extra == 'docs'
Requires-Dist: sphinx-autodoc-typehints<3.0,>=2.5.0; extra == 'docs'
Requires-Dist: sphinx-autorun<3.0,>=2.0.0; extra == 'docs'
Requires-Dist: sphinx-rtd-theme<4.0,>=3.0.2; extra == 'docs'
Provides-Extra: full
Requires-Dist: hyperopt<1.0,>=0.2.7; extra == 'full'
Requires-Dist: jupyter<2.0,>=1.1.1; extra == 'full'
Requires-Dist: ray[tune]<3.0,>=2.49.0; extra == 'full'
Requires-Dist: scikit-learn<2.0,>=1.7.1; extra == 'full'
Requires-Dist: torch<3.0,>=2.8.0; extra == 'full'
Provides-Extra: nn
Requires-Dist: hyperopt<1.0,>=0.2.7; extra == 'nn'
Requires-Dist: ray[tune]<3.0,>=2.49.0; extra == 'nn'
Requires-Dist: scikit-learn<2.0,>=1.7.1; extra == 'nn'
Requires-Dist: torch<3.0,>=2.8.0; extra == 'nn'
